jsonmetamodel/__init__.py
jsonmetamodel/fieldtypes.py
jsonmetamodel/metaclass.py
jsonmetamodel-0.1a0.dist-info/LICENSE
jsonmetamodel-0.1a0.dist-info/METADATA
jsonmetamodel-0.1a0.dist-info/WHEEL
jsonmetamodel-0.1a0.dist-info/top_level.txt
jsonmetamodel-0.1a0.dist-info/RECORD
