Metadata-Version: 2.1
Name: jsonmetamodel
Version: 0.1a0
Summary: Creates metaclasses for parameter definition and checking with taking respect to the jsonschema defined by https://json-schema.org/
Home-page: https://gitlab.com/david.scheliga/jsonschemamodel
Author: David Scheliga
Author-email: david.scheliga@gmx.de
License: GNU General Public License v3 (GPLv3)
Project-URL: Source Code Repository, https://gitlab.com/david.scheliga/jsonschemamodel
Keywords: jsonschema,dict,interfaces
Platform: UNKNOWN
Classifier: Development Status :: 3 - Alpha
Classifier: License :: OSI Approved :: GNU General Public License v3 (GPLv3)
Classifier: Programming Language :: Python :: 3.6
Requires-Dist: pandas
Requires-Dist: numpy
Requires-Dist: augmentedtree (>=0.2a0)
Requires-Dist: dicthandling (>=0.1b5)
